verilog/chapter3/addr_gen/addr_gen.v
module addr_gen 
#(  parameter MAX_DATA=256,
	localparam AWIDTH = $clog2(MAX_DATA)
) ( input en, clk, rst,
	output reg [AWIDTH-1:0] addr
);
	initial addr = 0;

	// async reset
	// increment address when enabled
	always @(posedge clk or posedge rst)
		if (rst)
			addr <= 0;
		else if (en) begin
			if ({'0, addr} == MAX_DATA-1)
				addr <= 0;
			else
				addr <= addr + 1;
		end
endmodule //addr_gen

verilog/chapter3/addr_gen/tb_addr_gen.v
`timescale 1ns/1ps

module tb_addr_gen;
    reg clk = 0;
    reg rst, en;
    wire [7:0] addr;

    addr_gen #(.MAX_DATA(256)) uut (
        .en(en),
        .clk(clk),
        .rst(rst),
        .addr(addr)
    );

    // 生成时钟（10ns周期）
    always #5 clk = ~clk;

    integer i;
    reg [7:0] expected;

    initial begin
        $dumpfile("tb_addr_gen.vcd");
        $dumpvars(0, tb_addr_gen);  // 记录所有信号

        // 初始化信号
        rst = 1;
        en = 0;
        #20 rst = 0;  // 复位释放

        // 测试1：en=0时地址不变
        en = 0;
        repeat(2) @(posedge clk);
        if (addr !== 8'd0) $error("Test1 Failed");
        else $display("Test1 Passed");

        // 测试2：地址递增至255后回绕
        en = 1;
        expected = 0;
        for (i = 0; i < 256; i = i + 1) begin
            @(posedge clk);
            #1;
            if (addr !== expected) $error("Test2 Failed at step %0d", i);
            expected = (expected == 255) ? 0 : expected + 1;
        end
        $display("Test2 Passed");

        // 测试3：回绕后继续递增
        @(posedge clk);
        #1;
        if (addr !== 8'd1) $error("Test3 Failed");
        else $display("Test3 Passed");

        // 测试4：en=0时地址不变
        en = 0;
        repeat(2) @(posedge clk);
        #1;
        if (addr !== 8'd1) $error("Test4 Failed");
        else $display("Test4 Passed");

        // 测试5：异步复位
        en = 1;
        @(negedge clk);  // 在时钟低电平触发复位
        rst = 1;
        #1;
        if (addr !== 8'd0) $error("Test5 Failed");
        @(posedge clk);
        #1;
        if (addr !== 8'd0) $error("Test5 Failed");
        rst = 0;
        $display("Test5 Passed");

        $display("All Tests Passed");
        $finish;
    end
endmodule

verilog/chapter3/addr_gen/tb_addr_gen.vcd
$date
	Sun Apr  6 15:17:33 2025
$end
$version
	Icarus Verilog
$end
$timescale
	1ps
$end
$scope module tb_addr_gen $end
$var wire 8 ! addr [7:0] $end
$var reg 1 " clk $end
$var reg 1 # en $end
$var reg 8 $ expected [7:0] $end
$var reg 1 % rst $end
$var integer 32 & i [31:0] $end
$scope module uut $end
$var wire 1 " clk $end
$var wire 1 # en $end
$var wire 1 % rst $end
$var reg 8 ' addr [7:0] $end
$upscope $end
$upscope $end
$enddefinitions $end
#0
$dumpvars
b0 '
bx &
1%
bx $
0#
0"
b0 !
$end
#5000
1"
#10000
0"
#15000
1"
#20000
0"
0%
#25000
1"
#30000
0"
#35000
b1 !
b1 '
b0 &
b0 $
1#
1"
#40000
0"
#45000
b10 !
b10 '
1"
#46000
b1 &
b1 $
#50000
0"
#55000
b11 !
b11 '
1"
#56000
b10 &
b10 $
#60000
0"
#65000
b100 !
b100 '
1"
#66000
b11 &
b11 $
#70000
0"
#75000
b101 !
b101 '
1"
#76000
b100 &
b100 $
#80000
0"
#85000
b110 !
b110 '
1"
#86000
b101 &
b101 $
#90000
0"
#95000
b111 !
b111 '
1"
#96000
b110 &
b110 $
#100000
0"
#105000
b1000 !
b1000 '
1"
#106000
b111 &
b111 $
#110000
0"
#115000
b1001 !
b1001 '
1"
#116000
b1000 &
b1000 $
#120000
0"
#125000
b1010 !
b1010 '
1"
#126000
b1001 &
b1001 $
#130000
0"
#135000
b1011 !
b1011 '
1"
#136000
b1010 &
b1010 $
#140000
0"
#145000
b1100 !
b1100 '
1"
#146000
b1011 &
b1011 $
#150000
0"
#155000
b1101 !
b1101 '
1"
#156000
b1100 &
b1100 $
#160000
0"
#165000
b1110 !
b1110 '
1"
#166000
b1101 &
b1101 $
#170000
0"
#175000
b1111 !
b1111 '
1"
#176000
b1110 &
b1110 $
#180000
0"
#185000
b10000 !
b10000 '
1"
#186000
b1111 &
b1111 $
#190000
0"
#195000
b10001 !
b10001 '
1"
#196000
b10000 &
b10000 $
#200000
0"
#205000
b10010 !
b10010 '
1"
#206000
b10001 &
b10001 $
#210000
0"
#215000
b10011 !
b10011 '
1"
#216000
b10010 &
b10010 $
#220000
0"
#225000
b10100 !
b10100 '
1"
#226000
b10011 &
b10011 $
#230000
0"
#235000
b10101 !
b10101 '
1"
#236000
b10100 &
b10100 $
#240000
0"
#245000
b10110 !
b10110 '
1"
#246000
b10101 &
b10101 $
#250000
0"
#255000
b10111 !
b10111 '
1"
#256000
b10110 &
b10110 $
#260000
0"
#265000
b11000 !
b11000 '
1"
#266000
b10111 &
b10111 $
#270000
0"
#275000
b11001 !
b11001 '
1"
#276000
b11000 &
b11000 $
#280000
0"
#285000
b11010 !
b11010 '
1"
#286000
b11001 &
b11001 $
#290000
0"
#295000
b11011 !
b11011 '
1"
#296000
b11010 &
b11010 $
#300000
0"
#305000
b11100 !
b11100 '
1"
#306000
b11011 &
b11011 $
#310000
0"
#315000
b11101 !
b11101 '
1"
#316000
b11100 &
b11100 $
#320000
0"
#325000
b11110 !
b11110 '
1"
#326000
b11101 &
b11101 $
#330000
0"
#335000
b11111 !
b11111 '
1"
#336000
b11110 &
b11110 $
#340000
0"
#345000
b100000 !
b100000 '
1"
#346000
b11111 &
b11111 $
#350000
0"
#355000
b100001 !
b100001 '
1"
#356000
b100000 &
b100000 $
#360000
0"
#365000
b100010 !
b100010 '
1"
#366000
b100001 &
b100001 $
#370000
0"
#375000
b100011 !
b100011 '
1"
#376000
b100010 &
b100010 $
#380000
0"
#385000
b100100 !
b100100 '
1"
#386000
b100011 &
b100011 $
#390000
0"
#395000
b100101 !
b100101 '
1"
#396000
b100100 &
b100100 $
#400000
0"
#405000
b100110 !
b100110 '
1"
#406000
b100101 &
b100101 $
#410000
0"
#415000
b100111 !
b100111 '
1"
#416000
b100110 &
b100110 $
#420000
0"
#425000
b101000 !
b101000 '
1"
#426000
b100111 &
b100111 $
#430000
0"
#435000
b101001 !
b101001 '
1"
#436000
b101000 &
b101000 $
#440000
0"
#445000
b101010 !
b101010 '
1"
#446000
b101001 &
b101001 $
#450000
0"
#455000
b101011 !
b101011 '
1"
#456000
b101010 &
b101010 $
#460000
0"
#465000
b101100 !
b101100 '
1"
#466000
b101011 &
b101011 $
#470000
0"
#475000
b101101 !
b101101 '
1"
#476000
b101100 &
b101100 $
#480000
0"
#485000
b101110 !
b101110 '
1"
#486000
b101101 &
b101101 $
#490000
0"
#495000
b101111 !
b101111 '
1"
#496000
b101110 &
b101110 $
#500000
0"
#505000
b110000 !
b110000 '
1"
#506000
b101111 &
b101111 $
#510000
0"
#515000
b110001 !
b110001 '
1"
#516000
b110000 &
b110000 $
#520000
0"
#525000
b110010 !
b110010 '
1"
#526000
b110001 &
b110001 $
#530000
0"
#535000
b110011 !
b110011 '
1"
#536000
b110010 &
b110010 $
#540000
0"
#545000
b110100 !
b110100 '
1"
#546000
b110011 &
b110011 $
#550000
0"
#555000
b110101 !
b110101 '
1"
#556000
b110100 &
b110100 $
#560000
0"
#565000
b110110 !
b110110 '
1"
#566000
b110101 &
b110101 $
#570000
0"
#575000
b110111 !
b110111 '
1"
#576000
b110110 &
b110110 $
#580000
0"
#585000
b111000 !
b111000 '
1"
#586000
b110111 &
b110111 $
#590000
0"
#595000
b111001 !
b111001 '
1"
#596000
b111000 &
b111000 $
#600000
0"
#605000
b111010 !
b111010 '
1"
#606000
b111001 &
b111001 $
#610000
0"
#615000
b111011 !
b111011 '
1"
#616000
b111010 &
b111010 $
#620000
0"
#625000
b111100 !
b111100 '
1"
#626000
b111011 &
b111011 $
#630000
0"
#635000
b111101 !
b111101 '
1"
#636000
b111100 &
b111100 $
#640000
0"
#645000
b111110 !
b111110 '
1"
#646000
b111101 &
b111101 $
#650000
0"
#655000
b111111 !
b111111 '
1"
#656000
b111110 &
b111110 $
#660000
0"
#665000
b1000000 !
b1000000 '
1"
#666000
b111111 &
b111111 $
#670000
0"
#675000
b1000001 !
b1000001 '
1"
#676000
b1000000 &
b1000000 $
#680000
0"
#685000
b1000010 !
b1000010 '
1"
#686000
b1000001 &
b1000001 $
#690000
0"
#695000
b1000011 !
b1000011 '
1"
#696000
b1000010 &
b1000010 $
#700000
0"
#705000
b1000100 !
b1000100 '
1"
#706000
b1000011 &
b1000011 $
#710000
0"
#715000
b1000101 !
b1000101 '
1"
#716000
b1000100 &
b1000100 $
#720000
0"
#725000
b1000110 !
b1000110 '
1"
#726000
b1000101 &
b1000101 $
#730000
0"
#735000
b1000111 !
b1000111 '
1"
#736000
b1000110 &
b1000110 $
#740000
0"
#745000
b1001000 !
b1001000 '
1"
#746000
b1000111 &
b1000111 $
#750000
0"
#755000
b1001001 !
b1001001 '
1"
#756000
b1001000 &
b1001000 $
#760000
0"
#765000
b1001010 !
b1001010 '
1"
#766000
b1001001 &
b1001001 $
#770000
0"
#775000
b1001011 !
b1001011 '
1"
#776000
b1001010 &
b1001010 $
#780000
0"
#785000
b1001100 !
b1001100 '
1"
#786000
b1001011 &
b1001011 $
#790000
0"
#795000
b1001101 !
b1001101 '
1"
#796000
b1001100 &
b1001100 $
#800000
0"
#805000
b1001110 !
b1001110 '
1"
#806000
b1001101 &
b1001101 $
#810000
0"
#815000
b1001111 !
b1001111 '
1"
#816000
b1001110 &
b1001110 $
#820000
0"
#825000
b1010000 !
b1010000 '
1"
#826000
b1001111 &
b1001111 $
#830000
0"
#835000
b1010001 !
b1010001 '
1"
#836000
b1010000 &
b1010000 $
#840000
0"
#845000
b1010010 !
b1010010 '
1"
#846000
b1010001 &
b1010001 $
#850000
0"
#855000
b1010011 !
b1010011 '
1"
#856000
b1010010 &
b1010010 $
#860000
0"
#865000
b1010100 !
b1010100 '
1"
#866000
b1010011 &
b1010011 $
#870000
0"
#875000
b1010101 !
b1010101 '
1"
#876000
b1010100 &
b1010100 $
#880000
0"
#885000
b1010110 !
b1010110 '
1"
#886000
b1010101 &
b1010101 $
#890000
0"
#895000
b1010111 !
b1010111 '
1"
#896000
b1010110 &
b1010110 $
#900000
0"
#905000
b1011000 !
b1011000 '
1"
#906000
b1010111 &
b1010111 $
#910000
0"
#915000
b1011001 !
b1011001 '
1"
#916000
b1011000 &
b1011000 $
#920000
0"
#925000
b1011010 !
b1011010 '
1"
#926000
b1011001 &
b1011001 $
#930000
0"
#935000
b1011011 !
b1011011 '
1"
#936000
b1011010 &
b1011010 $
#940000
0"
#945000
b1011100 !
b1011100 '
1"
#946000
b1011011 &
b1011011 $
#950000
0"
#955000
b1011101 !
b1011101 '
1"
#956000
b1011100 &
b1011100 $
#960000
0"
#965000
b1011110 !
b1011110 '
1"
#966000
b1011101 &
b1011101 $
#970000
0"
#975000
b1011111 !
b1011111 '
1"
#976000
b1011110 &
b1011110 $
#980000
0"
#985000
b1100000 !
b1100000 '
1"
#986000
b1011111 &
b1011111 $
#990000
0"
#995000
b1100001 !
b1100001 '
1"
#996000
b1100000 &
b1100000 $
#1000000
0"
#1005000
b1100010 !
b1100010 '
1"
#1006000
b1100001 &
b1100001 $
#1010000
0"
#1015000
b1100011 !
b1100011 '
1"
#1016000
b1100010 &
b1100010 $
#1020000
0"
#1025000
b1100100 !
b1100100 '
1"
#1026000
b1100011 &
b1100011 $
#1030000
0"
#1035000
b1100101 !
b1100101 '
1"
#1036000
b1100100 &
b1100100 $
#1040000
0"
#1045000
b1100110 !
b1100110 '
1"
#1046000
b1100101 &
b1100101 $
#1050000
0"
#1055000
b1100111 !
b1100111 '
1"
#1056000
b1100110 &
b1100110 $
#1060000
0"
#1065000
b1101000 !
b1101000 '
1"
#1066000
b1100111 &
b1100111 $
#1070000
0"
#1075000
b1101001 !
b1101001 '
1"
#1076000
b1101000 &
b1101000 $
#1080000
0"
#1085000
b1101010 !
b1101010 '
1"
#1086000
b1101001 &
b1101001 $
#1090000
0"
#1095000
b1101011 !
b1101011 '
1"
#1096000
b1101010 &
b1101010 $
#1100000
0"
#1105000
b1101100 !
b1101100 '
1"
#1106000
b1101011 &
b1101011 $
#1110000
0"
#1115000
b1101101 !
b1101101 '
1"
#1116000
b1101100 &
b1101100 $
#1120000
0"
#1125000
b1101110 !
b1101110 '
1"
#1126000
b1101101 &
b1101101 $
#1130000
0"
#1135000
b1101111 !
b1101111 '
1"
#1136000
b1101110 &
b1101110 $
#1140000
0"
#1145000
b1110000 !
b1110000 '
1"
#1146000
b1101111 &
b1101111 $
#1150000
0"
#1155000
b1110001 !
b1110001 '
1"
#1156000
b1110000 &
b1110000 $
#1160000
0"
#1165000
b1110010 !
b1110010 '
1"
#1166000
b1110001 &
b1110001 $
#1170000
0"
#1175000
b1110011 !
b1110011 '
1"
#1176000
b1110010 &
b1110010 $
#1180000
0"
#1185000
b1110100 !
b1110100 '
1"
#1186000
b1110011 &
b1110011 $
#1190000
0"
#1195000
b1110101 !
b1110101 '
1"
#1196000
b1110100 &
b1110100 $
#1200000
0"
#1205000
b1110110 !
b1110110 '
1"
#1206000
b1110101 &
b1110101 $
#1210000
0"
#1215000
b1110111 !
b1110111 '
1"
#1216000
b1110110 &
b1110110 $
#1220000
0"
#1225000
b1111000 !
b1111000 '
1"
#1226000
b1110111 &
b1110111 $
#1230000
0"
#1235000
b1111001 !
b1111001 '
1"
#1236000
b1111000 &
b1111000 $
#1240000
0"
#1245000
b1111010 !
b1111010 '
1"
#1246000
b1111001 &
b1111001 $
#1250000
0"
#1255000
b1111011 !
b1111011 '
1"
#1256000
b1111010 &
b1111010 $
#1260000
0"
#1265000
b1111100 !
b1111100 '
1"
#1266000
b1111011 &
b1111011 $
#1270000
0"
#1275000
b1111101 !
b1111101 '
1"
#1276000
b1111100 &
b1111100 $
#1280000
0"
#1285000
b1111110 !
b1111110 '
1"
#1286000
b1111101 &
b1111101 $
#1290000
0"
#1295000
b1111111 !
b1111111 '
1"
#1296000
b1111110 &
b1111110 $
#1300000
0"
#1305000
b10000000 !
b10000000 '
1"
#1306000
b1111111 &
b1111111 $
#1310000
0"
#1315000
b10000001 !
b10000001 '
1"
#1316000
b10000000 &
b10000000 $
#1320000
0"
#1325000
b10000010 !
b10000010 '
1"
#1326000
b10000001 &
b10000001 $
#1330000
0"
#1335000
b10000011 !
b10000011 '
1"
#1336000
b10000010 &
b10000010 $
#1340000
0"
#1345000
b10000100 !
b10000100 '
1"
#1346000
b10000011 &
b10000011 $
#1350000
0"
#1355000
b10000101 !
b10000101 '
1"
#1356000
b10000100 &
b10000100 $
#1360000
0"
#1365000
b10000110 !
b10000110 '
1"
#1366000
b10000101 &
b10000101 $
#1370000
0"
#1375000
b10000111 !
b10000111 '
1"
#1376000
b10000110 &
b10000110 $
#1380000
0"
#1385000
b10001000 !
b10001000 '
1"
#1386000
b10000111 &
b10000111 $
#1390000
0"
#1395000
b10001001 !
b10001001 '
1"
#1396000
b10001000 &
b10001000 $
#1400000
0"
#1405000
b10001010 !
b10001010 '
1"
#1406000
b10001001 &
b10001001 $
#1410000
0"
#1415000
b10001011 !
b10001011 '
1"
#1416000
b10001010 &
b10001010 $
#1420000
0"
#1425000
b10001100 !
b10001100 '
1"
#1426000
b10001011 &
b10001011 $
#1430000
0"
#1435000
b10001101 !
b10001101 '
1"
#1436000
b10001100 &
b10001100 $
#1440000
0"
#1445000
b10001110 !
b10001110 '
1"
#1446000
b10001101 &
b10001101 $
#1450000
0"
#1455000
b10001111 !
b10001111 '
1"
#1456000
b10001110 &
b10001110 $
#1460000
0"
#1465000
b10010000 !
b10010000 '
1"
#1466000
b10001111 &
b10001111 $
#1470000
0"
#1475000
b10010001 !
b10010001 '
1"
#1476000
b10010000 &
b10010000 $
#1480000
0"
#1485000
b10010010 !
b10010010 '
1"
#1486000
b10010001 &
b10010001 $
#1490000
0"
#1495000
b10010011 !
b10010011 '
1"
#1496000
b10010010 &
b10010010 $
#1500000
0"
#1505000
b10010100 !
b10010100 '
1"
#1506000
b10010011 &
b10010011 $
#1510000
0"
#1515000
b10010101 !
b10010101 '
1"
#1516000
b10010100 &
b10010100 $
#1520000
0"
#1525000
b10010110 !
b10010110 '
1"
#1526000
b10010101 &
b10010101 $
#1530000
0"
#1535000
b10010111 !
b10010111 '
1"
#1536000
b10010110 &
b10010110 $
#1540000
0"
#1545000
b10011000 !
b10011000 '
1"
#1546000
b10010111 &
b10010111 $
#1550000
0"
#1555000
b10011001 !
b10011001 '
1"
#1556000
b10011000 &
b10011000 $
#1560000
0"
#1565000
b10011010 !
b10011010 '
1"
#1566000
b10011001 &
b10011001 $
#1570000
0"
#1575000
b10011011 !
b10011011 '
1"
#1576000
b10011010 &
b10011010 $
#1580000
0"
#1585000
b10011100 !
b10011100 '
1"
#1586000
b10011011 &
b10011011 $
#1590000
0"
#1595000
b10011101 !
b10011101 '
1"
#1596000
b10011100 &
b10011100 $
#1600000
0"
#1605000
b10011110 !
b10011110 '
1"
#1606000
b10011101 &
b10011101 $
#1610000
0"
#1615000
b10011111 !
b10011111 '
1"
#1616000
b10011110 &
b10011110 $
#1620000
0"
#1625000
b10100000 !
b10100000 '
1"
#1626000
b10011111 &
b10011111 $
#1630000
0"
#1635000
b10100001 !
b10100001 '
1"
#1636000
b10100000 &
b10100000 $
#1640000
0"
#1645000
b10100010 !
b10100010 '
1"
#1646000
b10100001 &
b10100001 $
#1650000
0"
#1655000
b10100011 !
b10100011 '
1"
#1656000
b10100010 &
b10100010 $
#1660000
0"
#1665000
b10100100 !
b10100100 '
1"
#1666000
b10100011 &
b10100011 $
#1670000
0"
#1675000
b10100101 !
b10100101 '
1"
#1676000
b10100100 &
b10100100 $
#1680000
0"
#1685000
b10100110 !
b10100110 '
1"
#1686000
b10100101 &
b10100101 $
#1690000
0"
#1695000
b10100111 !
b10100111 '
1"
#1696000
b10100110 &
b10100110 $
#1700000
0"
#1705000
b10101000 !
b10101000 '
1"
#1706000
b10100111 &
b10100111 $
#1710000
0"
#1715000
b10101001 !
b10101001 '
1"
#1716000
b10101000 &
b10101000 $
#1720000
0"
#1725000
b10101010 !
b10101010 '
1"
#1726000
b10101001 &
b10101001 $
#1730000
0"
#1735000
b10101011 !
b10101011 '
1"
#1736000
b10101010 &
b10101010 $
#1740000
0"
#1745000
b10101100 !
b10101100 '
1"
#1746000
b10101011 &
b10101011 $
#1750000
0"
#1755000
b10101101 !
b10101101 '
1"
#1756000
b10101100 &
b10101100 $
#1760000
0"
#1765000
b10101110 !
b10101110 '
1"
#1766000
b10101101 &
b10101101 $
#1770000
0"
#1775000
b10101111 !
b10101111 '
1"
#1776000
b10101110 &
b10101110 $
#1780000
0"
#1785000
b10110000 !
b10110000 '
1"
#1786000
b10101111 &
b10101111 $
#1790000
0"
#1795000
b10110001 !
b10110001 '
1"
#1796000
b10110000 &
b10110000 $
#1800000
0"
#1805000
b10110010 !
b10110010 '
1"
#1806000
b10110001 &
b10110001 $
#1810000
0"
#1815000
b10110011 !
b10110011 '
1"
#1816000
b10110010 &
b10110010 $
#1820000
0"
#1825000
b10110100 !
b10110100 '
1"
#1826000
b10110011 &
b10110011 $
#1830000
0"
#1835000
b10110101 !
b10110101 '
1"
#1836000
b10110100 &
b10110100 $
#1840000
0"
#1845000
b10110110 !
b10110110 '
1"
#1846000
b10110101 &
b10110101 $
#1850000
0"
#1855000
b10110111 !
b10110111 '
1"
#1856000
b10110110 &
b10110110 $
#1860000
0"
#1865000
b10111000 !
b10111000 '
1"
#1866000
b10110111 &
b10110111 $
#1870000
0"
#1875000
b10111001 !
b10111001 '
1"
#1876000
b10111000 &
b10111000 $
#1880000
0"
#1885000
b10111010 !
b10111010 '
1"
#1886000
b10111001 &
b10111001 $
#1890000
0"
#1895000
b10111011 !
b10111011 '
1"
#1896000
b10111010 &
b10111010 $
#1900000
0"
#1905000
b10111100 !
b10111100 '
1"
#1906000
b10111011 &
b10111011 $
#1910000
0"
#1915000
b10111101 !
b10111101 '
1"
#1916000
b10111100 &
b10111100 $
#1920000
0"
#1925000
b10111110 !
b10111110 '
1"
#1926000
b10111101 &
b10111101 $
#1930000
0"
#1935000
b10111111 !
b10111111 '
1"
#1936000
b10111110 &
b10111110 $
#1940000
0"
#1945000
b11000000 !
b11000000 '
1"
#1946000
b10111111 &
b10111111 $
#1950000
0"
#1955000
b11000001 !
b11000001 '
1"
#1956000
b11000000 &
b11000000 $
#1960000
0"
#1965000
b11000010 !
b11000010 '
1"
#1966000
b11000001 &
b11000001 $
#1970000
0"
#1975000
b11000011 !
b11000011 '
1"
#1976000
b11000010 &
b11000010 $
#1980000
0"
#1985000
b11000100 !
b11000100 '
1"
#1986000
b11000011 &
b11000011 $
#1990000
0"
#1995000
b11000101 !
b11000101 '
1"
#1996000
b11000100 &
b11000100 $
#2000000
0"
#2005000
b11000110 !
b11000110 '
1"
#2006000
b11000101 &
b11000101 $
#2010000
0"
#2015000
b11000111 !
b11000111 '
1"
#2016000
b11000110 &
b11000110 $
#2020000
0"
#2025000
b11001000 !
b11001000 '
1"
#2026000
b11000111 &
b11000111 $
#2030000
0"
#2035000
b11001001 !
b11001001 '
1"
#2036000
b11001000 &
b11001000 $
#2040000
0"
#2045000
b11001010 !
b11001010 '
1"
#2046000
b11001001 &
b11001001 $
#2050000
0"
#2055000
b11001011 !
b11001011 '
1"
#2056000
b11001010 &
b11001010 $
#2060000
0"
#2065000
b11001100 !
b11001100 '
1"
#2066000
b11001011 &
b11001011 $
#2070000
0"
#2075000
b11001101 !
b11001101 '
1"
#2076000
b11001100 &
b11001100 $
#2080000
0"
#2085000
b11001110 !
b11001110 '
1"
#2086000
b11001101 &
b11001101 $
#2090000
0"
#2095000
b11001111 !
b11001111 '
1"
#2096000
b11001110 &
b11001110 $
#2100000
0"
#2105000
b11010000 !
b11010000 '
1"
#2106000
b11001111 &
b11001111 $
#2110000
0"
#2115000
b11010001 !
b11010001 '
1"
#2116000
b11010000 &
b11010000 $
#2120000
0"
#2125000
b11010010 !
b11010010 '
1"
#2126000
b11010001 &
b11010001 $
#2130000
0"
#2135000
b11010011 !
b11010011 '
1"
#2136000
b11010010 &
b11010010 $
#2140000
0"
#2145000
b11010100 !
b11010100 '
1"
#2146000
b11010011 &
b11010011 $
#2150000
0"
#2155000
b11010101 !
b11010101 '
1"
#2156000
b11010100 &
b11010100 $
#2160000
0"
#2165000
b11010110 !
b11010110 '
1"
#2166000
b11010101 &
b11010101 $
#2170000
0"
#2175000
b11010111 !
b11010111 '
1"
#2176000
b11010110 &
b11010110 $
#2180000
0"
#2185000
b11011000 !
b11011000 '
1"
#2186000
b11010111 &
b11010111 $
#2190000
0"
#2195000
b11011001 !
b11011001 '
1"
#2196000
b11011000 &
b11011000 $
#2200000
0"
#2205000
b11011010 !
b11011010 '
1"
#2206000
b11011001 &
b11011001 $
#2210000
0"
#2215000
b11011011 !
b11011011 '
1"
#2216000
b11011010 &
b11011010 $
#2220000
0"
#2225000
b11011100 !
b11011100 '
1"
#2226000
b11011011 &
b11011011 $
#2230000
0"
#2235000
b11011101 !
b11011101 '
1"
#2236000
b11011100 &
b11011100 $
#2240000
0"
#2245000
b11011110 !
b11011110 '
1"
#2246000
b11011101 &
b11011101 $
#2250000
0"
#2255000
b11011111 !
b11011111 '
1"
#2256000
b11011110 &
b11011110 $
#2260000
0"
#2265000
b11100000 !
b11100000 '
1"
#2266000
b11011111 &
b11011111 $
#2270000
0"
#2275000
b11100001 !
b11100001 '
1"
#2276000
b11100000 &
b11100000 $
#2280000
0"
#2285000
b11100010 !
b11100010 '
1"
#2286000
b11100001 &
b11100001 $
#2290000
0"
#2295000
b11100011 !
b11100011 '
1"
#2296000
b11100010 &
b11100010 $
#2300000
0"
#2305000
b11100100 !
b11100100 '
1"
#2306000
b11100011 &
b11100011 $
#2310000
0"
#2315000
b11100101 !
b11100101 '
1"
#2316000
b11100100 &
b11100100 $
#2320000
0"
#2325000
b11100110 !
b11100110 '
1"
#2326000
b11100101 &
b11100101 $
#2330000
0"
#2335000
b11100111 !
b11100111 '
1"
#2336000
b11100110 &
b11100110 $
#2340000
0"
#2345000
b11101000 !
b11101000 '
1"
#2346000
b11100111 &
b11100111 $
#2350000
0"
#2355000
b11101001 !
b11101001 '
1"
#2356000
b11101000 &
b11101000 $
#2360000
0"
#2365000
b11101010 !
b11101010 '
1"
#2366000
b11101001 &
b11101001 $
#2370000
0"
#2375000
b11101011 !
b11101011 '
1"
#2376000
b11101010 &
b11101010 $
#2380000
0"
#2385000
b11101100 !
b11101100 '
1"
#2386000
b11101011 &
b11101011 $
#2390000
0"
#2395000
b11101101 !
b11101101 '
1"
#2396000
b11101100 &
b11101100 $
#2400000
0"
#2405000
b11101110 !
b11101110 '
1"
#2406000
b11101101 &
b11101101 $
#2410000
0"
#2415000
b11101111 !
b11101111 '
1"
#2416000
b11101110 &
b11101110 $
#2420000
0"
#2425000
b11110000 !
b11110000 '
1"
#2426000
b11101111 &
b11101111 $
#2430000
0"
#2435000
b11110001 !
b11110001 '
1"
#2436000
b11110000 &
b11110000 $
#2440000
0"
#2445000
b11110010 !
b11110010 '
1"
#2446000
b11110001 &
b11110001 $
#2450000
0"
#2455000
b11110011 !
b11110011 '
1"
#2456000
b11110010 &
b11110010 $
#2460000
0"
#2465000
b11110100 !
b11110100 '
1"
#2466000
b11110011 &
b11110011 $
#2470000
0"
#2475000
b11110101 !
b11110101 '
1"
#2476000
b11110100 &
b11110100 $
#2480000
0"
#2485000
b11110110 !
b11110110 '
1"
#2486000
b11110101 &
b11110101 $
#2490000
0"
#2495000
b11110111 !
b11110111 '
1"
#2496000
b11110110 &
b11110110 $
#2500000
0"
#2505000
b11111000 !
b11111000 '
1"
#2506000
b11110111 &
b11110111 $
#2510000
0"
#2515000
b11111001 !
b11111001 '
1"
#2516000
b11111000 &
b11111000 $
#2520000
0"
#2525000
b11111010 !
b11111010 '
1"
#2526000
b11111001 &
b11111001 $
#2530000
0"
#2535000
b11111011 !
b11111011 '
1"
#2536000
b11111010 &
b11111010 $
#2540000
0"
#2545000
b11111100 !
b11111100 '
1"
#2546000
b11111011 &
b11111011 $
#2550000
0"
#2555000
b11111101 !
b11111101 '
1"
#2556000
b11111100 &
b11111100 $
#2560000
0"
#2565000
b11111110 !
b11111110 '
1"
#2566000
b11111101 &
b11111101 $
#2570000
0"
#2575000
b11111111 !
b11111111 '
1"
#2576000
b11111110 &
b11111110 $
#2580000
0"
#2585000
b0 !
b0 '
1"
#2586000
b11111111 &
b11111111 $
#2590000
0"
#2595000
b1 !
b1 '
1"
#2596000
b100000000 &
b0 $
#2600000
0"
#2605000
b10 !
b10 '
1"
#2606000
0#
#2610000
0"
#2615000
1"
#2620000
0"
#2625000
1"
#2626000
1#
#2630000
b0 !
b0 '
1%
0"
#2635000
1"
#2636000
0%
