verilog/chapter3/fifo/fifo.v
// address generator/counter
module addr_gen 
#(  parameter MAX_DATA=256,
	localparam AWIDTH = $clog2(MAX_DATA)
) ( input en, clk, rst,
	output reg [AWIDTH-1:0] addr
);
	initial addr = 0;

	// async reset
	// increment address when enabled
	always @(posedge clk or posedge rst)
		if (rst)
			addr <= 0;
		else if (en) begin
			if ({'0, addr} == MAX_DATA-1)
				addr <= 0;
			else
				addr <= addr + 1;
		end
endmodule //addr_gen

// Define our top level fifo entity
module fifo 
#(  parameter MAX_DATA=256,
	localparam AWIDTH = $clog2(MAX_DATA)
) ( input wen, ren, clk, rst,
	input [7:0] wdata,
	output reg [7:0] rdata,
	output reg [AWIDTH:0] count
);
	// fifo storage
	// sync read before write
	wire [AWIDTH-1:0] waddr, raddr;
	reg [7:0] data [MAX_DATA-1:0];
	always @(posedge clk) begin
		if (wen)
			data[waddr] <= wdata;
		rdata <= data[raddr];
	end // storage

	// addr_gen for both write and read addresses
	addr_gen #(.MAX_DATA(MAX_DATA))
	fifo_writer (
		.en     (wen),
		.clk    (clk),
		.rst    (rst),
		.addr   (waddr)
	);

	addr_gen #(.MAX_DATA(MAX_DATA))
	fifo_reader (
		.en     (ren),
		.clk    (clk),
		.rst    (rst),
		.addr   (raddr)
	);

	// status signals
	initial count = 0;

	always @(posedge clk or posedge rst) begin
		if (rst)
			count <= 0;
		else if (wen && !ren)
			count <= count + 1;
		else if (ren && !wen)
			count <= count - 1;
	end

endmodule

verilog/chapter3/fifo/fifo_tb.v
module fifo_tb;
    // 测试参数设置
    parameter MAX_DATA = 4;       // 使用较小深度便于测试
    localparam AWIDTH = $clog2(MAX_DATA);
    
    // 输入信号
    reg clk, rst;
    reg wen, ren;
    reg [7:0] wdata;
    
    // 输出信号
    wire [7:0] rdata;
    wire [AWIDTH:0] count;
    
    // 实例化被测FIFO
    fifo #(.MAX_DATA(MAX_DATA)) dut (
        .clk(clk),
        .rst(rst),
        .wen(wen),
        .ren(ren),
        .wdata(wdata),
        .rdata(rdata),
        .count(count)
    );
    
    // 生成时钟（周期10ns）
    initial clk = 0;
    always #5 clk = ~clk;
    
    // 主测试流程
    initial begin
        // 初始化信号
        wen = 0;
        ren = 0;
        wdata = 0;
        rst = 1;
        
        // 复位操作（15ns后释放）
        #15 rst = 0;
        
        // 测试用例1：基本写操作
        $display("\n=== Test 1: Basic write ===");
        wen = 1;
        repeat(MAX_DATA) begin
            wdata = $random;
            @(posedge clk);
            #1;
            $display("Write: 0x%h | Count: %0d", wdata, count);
        end
        wen = 0;
        
        // 验证计数
        if(count !== MAX_DATA)
            $display("Error: Expected count %0d, got %0d", MAX_DATA, count);
        
        // 测试用例2：基本读操作
        $display("\n=== Test 2: Basic read ===");
        ren = 1;
        repeat(MAX_DATA) begin
            @(posedge clk);
            #1;
            $display("Read: 0x%h | Count: %0d", rdata, count);
        end
        ren = 0;
        
        // 验证空状态
        if(count !== 0)
            $display("Error: Expected count 0, got %0d", count);
            
        // 测试用例3：同时读写
        $display("\n=== Test 3: Concurrent R/W ===");
        wen = 1;
        ren = 1;
        repeat(4) begin
            wdata = $random;
            @(posedge clk);
            #1;
            $display("Write: 0x%h | Read: 0x%h | Count: %0d", 
                    wdata, rdata, count);
        end
        wen = 0;
        ren = 0;
        
        // 测试用例4：边界条件测试
        $display("\n=== Test 4: Boundary cases ===");
        
        // 写满测试
        wen = 1;
        repeat(MAX_DATA+2) begin
            wdata = $urandom;
            @(posedge clk);
        end
        wen = 0;
        $display("Overflow count: %0d", count);
        
        // 读空测试
        ren = 1;
        repeat(MAX_DATA+2) @(posedge clk);
        ren = 0;
        $display("Underflow count: %0d", count);
        
        // 结束仿真
        #100;
        $display("\nTestbench completed");
        $finish;
    end
    
    // 波形记录（可选）
    initial begin
        $dumpfile("fifo.vcd");
        $dumpvars(0, fifo_tb);
    end
endmodule

verilog/chapter3/fifo/fifo.vcd
$date
	Wed Apr  8 09:22:09 2026
$end
$version
	Icarus Verilog
$end
$timescale
	1s
$end
$scope module fifo_tb $end
$var wire 8 ! rdata [7:0] $end
$var wire 3 " count [2:0] $end
$var parameter 32 # AWIDTH $end
$var parameter 32 $ MAX_DATA $end
$var reg 1 % clk $end
$var reg 1 & ren $end
$var reg 1 ' rst $end
$var reg 8 ( wdata [7:0] $end
$var reg 1 ) wen $end
$scope module dut $end
$var wire 1 % clk $end
$var wire 1 & ren $end
$var wire 1 ' rst $end
$var wire 8 * wdata [7:0] $end
$var wire 1 ) wen $end
$var wire 2 + waddr [1:0] $end
$var wire 2 , raddr [1:0] $end
$var parameter 32 - AWIDTH $end
$var parameter 32 . MAX_DATA $end
$var reg 3 / count [2:0] $end
$var reg 8 0 rdata [7:0] $end
$scope module fifo_reader $end
$var wire 1 % clk $end
$var wire 1 & en $end
$var wire 1 ' rst $end
$var parameter 32 1 AWIDTH $end
$var parameter 32 2 MAX_DATA $end
$var reg 2 3 addr [1:0] $end
$upscope $end
$scope module fifo_writer $end
$var wire 1 % clk $end
$var wire 1 ) en $end
$var wire 1 ' rst $end
$var parameter 32 4 AWIDTH $end
$var parameter 32 5 MAX_DATA $end
$var reg 2 6 addr [1:0] $end
$upscope $end
$upscope $end
$upscope $end
$enddefinitions $end
$comment Show the parameter values. $end
$dumpall
b100 5
b10 4
b100 2
b10 1
b100 .
b10 -
b100 $
b10 #
$end
#0
$dumpvars
b0 6
b0 3
bx 0
b0 /
b0 ,
b0 +
b0 *
0)
b0 (
1'
0&
0%
b0 "
bx !
$end
#5
1%
#10
0%
#15
b1 +
b1 6
b1 "
b1 /
1%
b100100 (
b100100 *
1)
0'
#16
b10000001 (
b10000001 *
#20
0%
#25
b10 "
b10 /
b10 +
b10 6
b100100 !
b100100 0
1%
#26
b1001 (
b1001 *
#30
0%
#35
b11 +
b11 6
b11 "
b11 /
1%
#36
b1100011 (
b1100011 *
#40
0%
#45
b100 "
b100 /
b0 +
b0 6
1%
#46
1&
0)
#50
0%
#55
b1 ,
b1 3
b11 "
b11 /
1%
#60
0%
#65
b10 "
b10 /
b10 ,
b10 3
b10000001 !
b10000001 0
1%
#70
0%
#75
b11 ,
b11 3
b1 "
b1 /
b1001 !
b1001 0
1%
#80
0%
#85
b0 "
b0 /
b0 ,
b0 3
b1100011 !
b1100011 0
1%
#86
b1101 (
b1101 *
1)
1&
#90
0%
#95
b1 +
b1 6
b1 ,
b1 3
b100100 !
b100100 0
1%
#96
b10001101 (
b10001101 *
#100
0%
#105
b10 ,
b10 3
b10 +
b10 6
b10000001 !
b10000001 0
1%
#106
b1100101 (
b1100101 *
#110
0%
#115
b11 +
b11 6
b11 ,
b11 3
b1001 !
b1001 0
1%
#116
b10010 (
b10010 *
#120
0%
#125
b0 ,
b0 3
b0 +
b0 6
b1100011 !
b1100011 0
1%
#126
b100100 (
b100100 *
0&
1)
#130
0%
#135
b1 +
b1 6
b1 "
b1 /
b1101 !
b1101 0
b10000001 (
b10000001 *
1%
#140
0%
#145
b10 "
b10 /
b10 +
b10 6
b10000001 !
b10000001 0
b1001 (
b1001 *
1%
#150
0%
#155
b11 +
b11 6
b11 "
b11 /
b1100011 (
b1100011 *
1%
#160
0%
#165
b100 "
b100 /
b0 +
b0 6
b1101 (
b1101 *
1%
#170
0%
#175
b1 +
b1 6
b101 "
b101 /
b10001101 (
b10001101 *
1%
#180
0%
#185
b100 "
b100 /
b1 ,
b1 3
b10001101 !
b10001101 0
1&
0)
1%
#190
0%
#195
b10 ,
b10 3
b11 "
b11 /
1%
#200
0%
#205
b10 "
b10 /
b11 ,
b11 3
b1100011 !
b1100011 0
1%
#210
0%
#215
b0 ,
b0 3
b1 "
b1 /
1%
#220
0%
#225
b0 "
b0 /
b1 ,
b1 3
b10001101 !
b10001101 0
1%
#230
0%
#235
b10 ,
b10 3
b111 "
b111 /
1%
#240
0%
#245
b1100011 !
b1100011 0
0&
1%
