verilog/chapter4/uart/rx.v
`timescale 1ns / 1ps

module uart_rx (
    input wire clk,           // System clock
    input wire rst_n,         // Active low reset
    input wire rx,            // Serial input
    output reg rx_ready,      // Data ready signal
    output reg [7:0] rx_data  // Received data
);

    // Parameters for UART configuration
    parameter CLK_FREQ = 50000000;  // 50MHz system clock
    parameter BAUD_RATE = 115200;   // Baud rate
    parameter CLKS_PER_BIT = CLK_FREQ / BAUD_RATE;
    
    // State machine states
    localparam IDLE = 3'b000;
    localparam START = 3'b001;
    localparam DATA = 3'b010;
    localparam STOP = 3'b011;
    localparam CLEANUP = 3'b100;
    
    // Internal registers
    reg [2:0] state;
    reg [15:0] clk_count;
    reg [2:0] bit_index;
    reg [7:0] rx_data_reg;
    
    // State machine
    always @(posedge clk or negedge rst_n) begin
        if (!rst_n) begin
            state <= IDLE;
            clk_count <= 0;
            bit_index <= 0;
            rx_data_reg <= 0;
            rx_ready <= 1'b0;
            rx_data <= 8'h00;
        end else begin
            case (state)
                IDLE: begin
                    rx_ready <= 1'b0;
                    clk_count <= 0;
                    bit_index <= 0;
                    
                    // Detect start bit (falling edge on rx)
                    if (rx == 1'b0) begin
                        state <= START;
                    end
                end
                
                START: begin
                    // Wait for middle of start bit
                    if (clk_count < (CLKS_PER_BIT - 1) / 2) begin
                        clk_count <= clk_count + 1;
                    end else begin
                        // Check if start bit is still low
                        if (rx == 1'b0) begin
                            // Reset counter for data bits
                            clk_count <= 0;
                            state <= DATA;
                        end else begin
                            // False start, go back to idle
                            state <= IDLE;
                        end
                    end
                end
                
                DATA: begin
                    // Wait for middle of data bit
                    if (clk_count < CLKS_PER_BIT - 1) begin
                        clk_count <= clk_count + 1;
                    end else begin
                        clk_count <= 0;
                        
                        // Sample the data bit
                        rx_data_reg[bit_index] <= rx;
                        
                        // Check if we have received all bits
                        if (bit_index < 7) begin
                            bit_index <= bit_index + 1;
                        end else begin
                            bit_index <= 0;
                            state <= STOP;
                        end
                    end
                end
                
                STOP: begin
                    // Wait for middle of stop bit
                    if (clk_count < CLKS_PER_BIT - 1) begin
                        clk_count <= clk_count + 1;
                    end else begin
                        // Check if stop bit is high
                        if (rx == 1'b1) begin
                            rx_ready <= 1'b1;
                            rx_data <= rx_data_reg;
                        end
                        
                        clk_count <= 0;
                        state <= CLEANUP;
                    end
                end
                
                CLEANUP: begin
                    // Wait one clock cycle to clear rx_ready
                    state <= IDLE;
                    rx_ready <= 1'b0;
                end
                
                default: begin
                    state <= IDLE;
                end
            endcase
        end
    end

endmodule

verilog/chapter4/uart/tx.v
`timescale 1ns / 1ps

module uart_tx (
    input wire clk,           // System clock
    input wire rst_n,         // Active low reset
    input wire tx_start,      // Start transmission signal
    input wire [7:0] tx_data, // Data to transmit
    output reg tx_done,       // Transmission complete signal
    output reg tx             // Serial output
);

    // Parameters for UART configuration
    parameter CLK_FREQ = 50000000;  // 50MHz system clock
    parameter BAUD_RATE = 115200;   // Baud rate
    parameter CLKS_PER_BIT = CLK_FREQ / BAUD_RATE;
    
    // State machine states
    localparam IDLE = 2'b00;
    localparam START = 2'b01;
    localparam DATA = 2'b10;
    localparam STOP = 2'b11;
    
    // Internal registers
    reg [1:0] state;
    reg [1:0] next_state;
    reg [15:0] clk_count;
    reg [2:0] bit_index;
    reg [7:0] tx_data_reg;
    
    // State machine
    always @(posedge clk or negedge rst_n) begin
        if (!rst_n) begin
            state <= IDLE;
            clk_count <= 0;
            bit_index <= 0;
            tx_data_reg <= 0;
            tx <= 1'b1;  // Idle state is high
            tx_done <= 1'b0;
        end else begin
            case (state)
                IDLE: begin
                    tx <= 1'b1;  // Idle state is high
                    tx_done <= 1'b0;
                    clk_count <= 0;
                    bit_index <= 0;
                    
                    if (tx_start) begin
                        tx_data_reg <= tx_data;
                        state <= START;
                    end
                end
                
                START: begin
                    tx <= 1'b0;  // Start bit is low
                    
                    // Wait for one bit period
                    if (clk_count < CLKS_PER_BIT - 1) begin
                        clk_count <= clk_count + 1;
                    end else begin
                        clk_count <= 0;
                        state <= DATA;
                    end
                end
                
                DATA: begin
                    tx <= tx_data_reg[bit_index];
                    
                    // Wait for one bit period
                    if (clk_count < CLKS_PER_BIT - 1) begin
                        clk_count <= clk_count + 1;
                    end else begin
                        clk_count <= 0;
                        
                        // Check if we have sent all bits
                        if (bit_index < 7) begin
                            bit_index <= bit_index + 1;
                        end else begin
                            bit_index <= 0;
                            state <= STOP;
                        end
                    end
                end
                
                STOP: begin
                    tx <= 1'b1;  // Stop bit is high
                    
                    // Wait for one bit period
                    if (clk_count < CLKS_PER_BIT - 1) begin
                        clk_count <= clk_count + 1;
                    end else begin
                        tx_done <= 1'b1;
                        clk_count <= 0;
                        state <= IDLE;
                    end
                end
                
                default: begin
                    state <= IDLE;
                end
            endcase
        end
    end

endmodule

verilog/chapter4/uart/uart_tb.v
`timescale 1ns / 1ps

module uart_tb;

    // Parameters
    parameter CLK_PERIOD = 20;    // 50MHz clock (20ns period)
    parameter BAUD_RATE = 115200;
    parameter BIT_PERIOD = 1000000000 / BAUD_RATE;  // Bit period in ns
    
    // Testbench signals
    reg clk;
    reg rst_n;
    wire rx;
    wire rx_ready;
    wire [7:0] rx_data;
    
    // Test control signals
    reg [7:0] test_data;
    reg tx_start;
    wire tx_done;
    
    // Instantiate UART transmitter (to generate test signals)
    uart_tx #(
        .CLK_FREQ(50000000),
        .BAUD_RATE(BAUD_RATE)
    ) uart_tx_inst (
        .clk(clk),
        .rst_n(rst_n),
        .tx_start(tx_start),
        .tx_data(test_data),
        .tx_done(tx_done),
        .tx(rx)  // Connect TX output to RX input
    );
    
    // Instantiate UART receiver
    uart_rx #(
        .CLK_FREQ(50000000),
        .BAUD_RATE(BAUD_RATE)
    ) uut (
        .clk(clk),
        .rst_n(rst_n),
        .rx(rx),
        .rx_ready(rx_ready),
        .rx_data(rx_data)
    );
    
    // Clock generation
    initial begin
        clk = 0;
        forever #(CLK_PERIOD/2) clk = ~clk;
    end
    
    // Test sequence
    initial begin
        // Initialize signals
        rst_n = 0;
        tx_start = 0;
        test_data = 8'h00;
        
        // Apply reset
        #100;
        rst_n = 1;
        #100;
        
        // Test case 1: Send character 'A' (0x41)
        test_data = 8'h41;
        tx_start = 1;
        #CLK_PERIOD;
        tx_start = 0;
        
        // Wait for transmission to complete
        @(posedge tx_done);
        #(BIT_PERIOD * 2);
        
        // Verify received data
        if (rx_data !== 8'h41 || rx_ready !== 1'b1) 
            $error("Test 1 Failed: Received 0x%h, Expected 0x41", rx_data);
        
        // Test case 2: Send character 'Z' (0x5A)
        test_data = 8'h5A;
        tx_start = 1;
        #CLK_PERIOD;
        tx_start = 0;
        
        // Wait for transmission to complete
        @(posedge tx_done);
        #(BIT_PERIOD * 2);
        
        // Verify received data
        if (rx_data !== 8'h5A || rx_ready !== 1'b1) 
            $error("Test 2 Failed: Received 0x%h, Expected 0x5A", rx_data);
        
        // Test case 3: Send random data
        test_data = 8'hA5;
        tx_start = 1;
        #CLK_PERIOD;
        tx_start = 0;
        
        // Wait for transmission to complete
        @(posedge tx_done);
        #(BIT_PERIOD * 2);
        
        // Verify received data
        if (rx_data !== 8'hA5 || rx_ready !== 1'b1) 
            $error("Test 3 Failed: Received 0x%h, Expected 0xA5", rx_data);
        
        // End simulation
        $display("All tests completed successfully");
        $finish;
    end
    
    // Monitor signals
    initial begin
        $monitor("Time: %t, RX: %b, Data: 0x%h, Ready: %b",
                $time, rx, rx_data, rx_ready);
    end
    
    // Generate VCD file for waveform viewing
    initial begin
        $dumpfile("uart_tb.vcd");
        $dumpvars(0, uart_tb);
    end

endmodule

verilog/chapter4/uart/uart_tb.vcd
$date
	Sun Apr  6 16:39:15 2025
$end
$version
	Icarus Verilog
$end
$timescale
	1ps
$end
$scope module uart_tb $end
$var wire 1 ! tx_done $end
$var wire 1 " rx_ready $end
$var wire 8 # rx_data [7:0] $end
$var wire 1 $ rx $end
$var reg 1 % clk $end
$var reg 1 & rst_n $end
$var reg 8 ' test_data [7:0] $end
$var reg 1 ( tx_start $end
$scope module uart_tx_inst $end
$var wire 1 % clk $end
$var wire 1 & rst_n $end
$var wire 8 ) tx_data [7:0] $end
$var wire 1 ( tx_start $end
$var reg 3 * bit_index [2:0] $end
$var reg 16 + clk_count [15:0] $end
$var reg 2 , state [1:0] $end
$var reg 1 $ tx $end
$var reg 8 - tx_data_reg [7:0] $end
$var reg 1 ! tx_done $end
$upscope $end
$scope module uut $end
$var wire 1 % clk $end
$var wire 1 & rst_n $end
$var wire 1 $ rx $end
$var reg 3 . bit_index [2:0] $end
$var reg 16 / clk_count [15:0] $end
$var reg 8 0 rx_data [7:0] $end
$var reg 8 1 rx_data_reg [7:0] $end
$var reg 1 " rx_ready $end
$var reg 3 2 state [2:0] $end
$upscope $end
$upscope $end
$enddefinitions $end
#0
$dumpvars
b0 2
b0 1
b0 0
b0 /
b0 .
b0 -
b0 ,
b0 +
b0 *
b0 )
0(
b0 '
0&
0%
1$
b0 #
0"
0!
$end
#10000
1%
#20000
0%
#30000
1%
#40000
0%
#50000
1%
#60000
0%
#70000
1%
#80000
0%
#90000
1%
#100000
0%
1&
#110000
1%
#120000
0%
#130000
1%
#140000
0%
#150000
1%
#160000
0%
#170000
1%
#180000
0%
#190000
1%
#200000
0%
1(
b1000001 '
b1000001 )
#210000
b1 ,
b1000001 -
1%
#220000
0%
0(
#230000
b1 +
0$
1%
#240000
0%
#250000
b1 2
b10 +
1%
#260000
0%
#270000
b11 +
b1 /
1%
#280000
0%
#290000
b10 /
b100 +
1%
#300000
0%
#310000
b101 +
b11 /
1%
#320000
0%
#330000
b100 /
b110 +
1%
#340000
0%
#350000
b111 +
b101 /
1%
#360000
0%
#370000
b110 /
b1000 +
1%
#380000
0%
#390000
b1001 +
b111 /
1%
#400000
0%
#410000
b1000 /
b1010 +
1%
#420000
0%
#430000
b1011 +
b1001 /
1%
#440000
0%
#450000
b1010 /
b1100 +
1%
#460000
0%
#470000
b1101 +
b1011 /
1%
#480000
0%
#490000
b1100 /
b1110 +
1%
#500000
0%
#510000
b1111 +
b1101 /
1%
#520000
0%
#530000
b1110 /
b10000 +
1%
#540000
0%
#550000
b10001 +
b1111 /
1%
#560000
0%
#570000
b10000 /
b10010 +
1%
#580000
0%
#590000
b10011 +
b10001 /
1%
#600000
0%
#610000
b10010 /
b10100 +
1%
#620000
0%
#630000
b10101 +
b10011 /
1%
#640000
0%
#650000
b10100 /
b10110 +
1%
#660000
0%
#670000
b10111 +
b10101 /
1%
#680000
0%
#690000
b10110 /
b11000 +
1%
#700000
0%
#710000
b11001 +
b10111 /
1%
#720000
0%
#730000
b11000 /
b11010 +
1%
#740000
0%
#750000
b11011 +
b11001 /
1%
#760000
0%
#770000
b11010 /
b11100 +
1%
#780000
0%
#790000
b11101 +
b11011 /
1%
#800000
0%
#810000
b11100 /
b11110 +
1%
#820000
0%
#830000
b11111 +
b11101 /
1%
#840000
0%
#850000
b11110 /
b100000 +
1%
#860000
0%
#870000
b100001 +
b11111 /
1%
#880000
0%
#890000
b100000 /
b100010 +
1%
#900000
0%
#910000
b100011 +
b100001 /
1%
#920000
0%
#930000
b100010 /
b100100 +
1%
#940000
0%
#950000
b100101 +
b100011 /
1%
#960000
0%
#970000
b100100 /
b100110 +
1%
#980000
0%
#990000
b100111 +
b100101 /
1%
#1000000
0%
#1010000
b100110 /
b101000 +
1%
#1020000
0%
#1030000
b101001 +
b100111 /
1%
#1040000
0%
#1050000
b101000 /
b101010 +
1%
#1060000
0%
#1070000
b101011 +
b101001 /
1%
#1080000
0%
#1090000
b101010 /
b101100 +
1%
#1100000
0%
#1110000
b101101 +
b101011 /
1%
#1120000
0%
#1130000
b101100 /
b101110 +
1%
#1140000
0%
#1150000
b101111 +
b101101 /
1%
#1160000
0%
#1170000
b101110 /
b110000 +
1%
#1180000
0%
#1190000
b110001 +
b101111 /
1%
#1200000
0%
#1210000
b110000 /
b110010 +
1%
#1220000
0%
#1230000
b110011 +
b110001 /
1%
#1240000
0%
#1250000
b110010 /
b110100 +
1%
#1260000
0%
#1270000
b110101 +
b110011 /
1%
#1280000
0%
#1290000
b110100 /
b110110 +
1%
#1300000
0%
#1310000
b110111 +
b110101 /
1%
#1320000
0%
#1330000
b110110 /
b111000 +
1%
#1340000
0%
#1350000
b111001 +
b110111 /
1%
#1360000
0%
#1370000
b111000 /
b111010 +
1%
#1380000
0%
#1390000
b111011 +
b111001 /
1%
#1400000
0%
#1410000
b111010 /
b111100 +
1%
#1420000
0%
#1430000
b111101 +
b111011 /
1%
#1440000
0%
#1450000
b111100 /
b111110 +
1%
#1460000
0%
#1470000
b111111 +
b111101 /
1%
#1480000
0%
#1490000
b111110 /
b1000000 +
1%
#1500000
0%
#1510000
b1000001 +
b111111 /
1%
#1520000
0%
#1530000
b1000000 /
b1000010 +
1%
#1540000
0%
#1550000
b1000011 +
b1000001 /
1%
#1560000
0%
#1570000
b1000010 /
b1000100 +
1%
#1580000
0%
#1590000
b1000101 +
b1000011 /
1%
#1600000
0%
#1610000
b1000100 /
b1000110 +
1%
#1620000
0%
#1630000
b1000111 +
b1000101 /
1%
#1640000
0%
#1650000
b1000110 /
b1001000 +
1%
#1660000
0%
#1670000
b1001001 +
b1000111 /
1%
#1680000
0%
#1690000
b1001000 /
b1001010 +
1%
#1700000
0%
#1710000
b1001011 +
b1001001 /
1%
#1720000
0%
#1730000
b1001010 /
b1001100 +
1%
#1740000
0%
#1750000
b1001101 +
b1001011 /
1%
#1760000
0%
#1770000
b1001100 /
b1001110 +
1%
#1780000
0%
#1790000
b1001111 +
b1001101 /
1%
#1800000
0%
#1810000
b1001110 /
b1010000 +
1%
#1820000
0%
#1830000
b1010001 +
b1001111 /
1%
#1840000
0%
#1850000
b1010000 /
b1010010 +
1%
#1860000
0%
#1870000
b1010011 +
b1010001 /
1%
#1880000
0%
#1890000
b1010010 /
b1010100 +
1%
#1900000
0%
#1910000
b1010101 +
b1010011 /
1%
#1920000
0%
#1930000
b1010100 /
b1010110 +
1%
#1940000
0%
#1950000
b1010111 +
b1010101 /
1%
#1960000
0%
#1970000
b1010110 /
b1011000 +
1%
#1980000
0%
#1990000
b1011001 +
b1010111 /
1%
#2000000
0%
#2010000
b1011000 /
b1011010 +
1%
#2020000
0%
#2030000
b1011011 +
b1011001 /
1%
#2040000
0%
#2050000
b1011010 /
b1011100 +
1%
#2060000
0%
#2070000
b1011101 +
b1011011 /
1%
#2080000
0%
#2090000
b1011100 /
b1011110 +
1%
#2100000
0%
#2110000
b1011111 +
b1011101 /
1%
#2120000
0%
#2130000
b1011110 /
b1100000 +
1%
#2140000
0%
#2150000
b1100001 +
b1011111 /
1%
#2160000
0%
#2170000
b1100000 /
b1100010 +
1%
#2180000
0%
#2190000
b1100011 +
b1100001 /
1%
#2200000
0%
#2210000
b1100010 /
b1100100 +
1%
#2220000
0%
#2230000
b1100101 +
b1100011 /
1%
#2240000
0%
#2250000
b1100100 /
b1100110 +
1%
#2260000
0%
#2270000
b1100111 +
b1100101 /
1%
#2280000
0%
#2290000
b1100110 /
b1101000 +
1%
#2300000
0%
#2310000
b1101001 +
b1100111 /
1%
#2320000
0%
#2330000
b1101000 /
b1101010 +
1%
#2340000
0%
#2350000
b1101011 +
b1101001 /
1%
#2360000
0%
#2370000
b1101010 /
b1101100 +
1%
#2380000
0%
#2390000
b1101101 +
b1101011 /
1%
#2400000
0%
#2410000
b1101100 /
b1101110 +
1%
#2420000
0%
#2430000
b1101111 +
b1101101 /
1%
#2440000
0%
#2450000
b1101110 /
b1110000 +
1%
#2460000
0%
#2470000
b1110001 +
b1101111 /
1%
#2480000
0%
#2490000
b1110000 /
b1110010 +
1%
#2500000
0%
#2510000
b1110011 +
b1110001 /
1%
#2520000
0%
#2530000
b1110010 /
b1110100 +
1%
#2540000
0%
#2550000
b1110101 +
b1110011 /
1%
#2560000
0%
#2570000
b1110100 /
b1110110 +
1%
#2580000
0%
#2590000
b1110111 +
b1110101 /
1%
#2600000
0%
#2610000
b1110110 /
b1111000 +
1%
#2620000
0%
#2630000
b1111001 +
b1110111 /
1%
#2640000
0%
#2650000
b1111000 /
b1111010 +
1%
#2660000
0%
#2670000
b1111011 +
b1111001 /
1%
#2680000
0%
#2690000
b1111010 /
b1111100 +
1%
#2700000
0%
#2710000
b1111101 +
b1111011 /
1%
#2720000
0%
#2730000
b1111100 /
b1111110 +
1%
#2740000
0%
#2750000
b1111111 +
b1111101 /
1%
#2760000
0%
#2770000
b1111110 /
b10000000 +
1%
#2780000
0%
#2790000
b10000001 +
b1111111 /
1%
#2800000
0%
#2810000
b10000000 /
b10000010 +
1%
#2820000
0%
#2830000
b10000011 +
b10000001 /
1%
#2840000
0%
#2850000
b10000010 /
b10000100 +
1%
#2860000
0%
#2870000
b10000101 +
b10000011 /
1%
#2880000
0%
#2890000
b10000100 /
b10000110 +
1%
#2900000
0%
#2910000
b10000111 +
b10000101 /
1%
#2920000
0%
#2930000
b10000110 /
b10001000 +
1%
#2940000
0%
#2950000
b10001001 +
b10000111 /
1%
#2960000
0%
#2970000
b10001000 /
b10001010 +
1%
#2980000
0%
#2990000
b10001011 +
b10001001 /
1%
#3000000
0%
#3010000
b10001010 /
b10001100 +
1%
#3020000
0%
#3030000
b10001101 +
b10001011 /
1%
#3040000
0%
#3050000
b10001100 /
b10001110 +
1%
#3060000
0%
#3070000
b10001111 +
b10001101 /
1%
#3080000
0%
#3090000
b10001110 /
b10010000 +
1%
#3100000
0%
#3110000
b10010001 +
b10001111 /
1%
#3120000
0%
#3130000
b10010000 /
b10010010 +
1%
#3140000
0%
#3150000
b10010011 +
b10010001 /
1%
#3160000
0%
#3170000
b10010010 /
b10010100 +
1%
#3180000
0%
#3190000
b10010101 +
b10010011 /
1%
#3200000
0%
#3210000
b10010100 /
b10010110 +
1%
#3220000
0%
#3230000
b10010111 +
b10010101 /
1%
#3240000
0%
#3250000
b10010110 /
b10011000 +
1%
#3260000
0%
#3270000
b10011001 +
b10010111 /
1%
#3280000
0%
#3290000
b10011000 /
b10011010 +
1%
#3300000
0%
#3310000
b10011011 +
b10011001 /
1%
#3320000
0%
#3330000
b10011010 /
b10011100 +
1%
#3340000
0%
#3350000
b10011101 +
b10011011 /
1%
#3360000
0%
#3370000
b10011100 /
b10011110 +
1%
#3380000
0%
#3390000
b10011111 +
b10011101 /
1%
#3400000
0%
#3410000
b10011110 /
b10100000 +
1%
#3420000
0%
#3430000
b10100001 +
b10011111 /
1%
#3440000
0%
#3450000
b10100000 /
b10100010 +
1%
#3460000
0%
#3470000
b10100011 +
b10100001 /
1%
#3480000
0%
#3490000
b10100010 /
b10100100 +
1%
#3500000
0%
#3510000
b10100101 +
b10100011 /
1%
#3520000
0%
#3530000
b10100100 /
b10100110 +
1%
#3540000
0%
#3550000
b10100111 +
b10100101 /
1%
#3560000
0%
#3570000
b10100110 /
b10101000 +
1%
#3580000
0%
#3590000
b10101001 +
b10100111 /
1%
#3600000
0%
#3610000
b10101000 /
b10101010 +
1%
#3620000
0%
#3630000
b10101011 +
b10101001 /
1%
#3640000
0%
#3650000
b10101010 /
b10101100 +
1%
#3660000
0%
#3670000
b10101101 +
b10101011 /
1%
#3680000
0%
#3690000
b10101100 /
b10101110 +
1%
#3700000
0%
#3710000
b10101111 +
b10101101 /
1%
#3720000
0%
#3730000
b10101110 /
b10110000 +
1%
#3740000
0%
#3750000
b10110001 +
b10101111 /
1%
#3760000
0%
#3770000
b10110000 /
b10110010 +
1%
#3780000
0%
#3790000
b10110011 +
b10110001 /
1%
#3800000
0%
#3810000
b10110010 /
b10110100 +
1%
#3820000
0%
#3830000
b10110101 +
b10110011 /
1%
#3840000
0%
#3850000
b10110100 /
b10110110 +
1%
#3860000
0%
#3870000
b10110111 +
b10110101 /
1%
#3880000
0%
#3890000
b10110110 /
b10111000 +
1%
#3900000
0%
#3910000
b10111001 +
b10110111 /
1%
#3920000
0%
#3930000
b10111000 /
b10111010 +
1%
#3940000
0%
#3950000
b10111011 +
b10111001 /
1%
#3960000
0%
#3970000
b10111010 /
b10111100 +
1%
#3980000
0%
#3990000
b10111101 +
b10111011 /
1%
#4000000
0%
#4010000
b10111100 /
b10111110 +
1%
#4020000
0%
#4030000
b10111111 +
b10111101 /
1%
#4040000
0%
#4050000
b10111110 /
b11000000 +
1%
#4060000
0%
#4070000
b11000001 +
b10111111 /
1%
#4080000
0%
#4090000
b11000000 /
b11000010 +
1%
#4100000
0%
#4110000
b11000011 +
b11000001 /
1%
#4120000
0%
#4130000
b11000010 /
b11000100 +
1%
#4140000
0%
#4150000
b11000101 +
b11000011 /
1%
#4160000
0%
#4170000
b11000100 /
b11000110 +
1%
#4180000
0%
#4190000
b11000111 +
b11000101 /
1%
#4200000
0%
#4210000
b11000110 /
b11001000 +
1%
#4220000
0%
#4230000
b11001001 +
b11000111 /
1%
#4240000
0%
#4250000
b11001000 /
b11001010 +
1%
#4260000
0%
#4270000
b11001011 +
b11001001 /
1%
#4280000
0%
#4290000
b11001010 /
b11001100 +
1%
#4300000
0%
#4310000
b11001101 +
b11001011 /
1%
#4320000
0%
#4330000
b11001100 /
b11001110 +
1%
#4340000
0%
#4350000
b11001111 +
b11001101 /
1%
#4360000
0%
#4370000
b11001110 /
b11010000 +
1%
#4380000
0%
#4390000
b11010001 +
b11001111 /
1%
#4400000
0%
#4410000
b11010000 /
b11010010 +
1%
#4420000
0%
#4430000
b11010011 +
b11010001 /
1%
#4440000
0%
#4450000
b11010010 /
b11010100 +
1%
#4460000
0%
#4470000
b11010101 +
b11010011 /
1%
#4480000
0%
#4490000
b11010100 /
b11010110 +
1%
#4500000
0%
#4510000
b11010111 +
b11010101 /
1%
#4520000
0%
#4530000
b11010110 /
b11011000 +
1%
#4540000
0%
#4550000
b11011001 +
b11010111 /
1%
#4560000
0%
#4570000
b11011000 /
b11011010 +
1%
#4580000
0%
#4590000
b11011011 +
b10 2
b0 /
1%
#4600000
0%
#4610000
b1 /
b11011100 +
1%
#4620000
0%
#4630000
b11011101 +
b10 /
1%
#4640000
0%
#4650000
b11 /
b11011110 +
1%
#4660000
0%
#4670000
b11011111 +
b100 /
1%
#4680000
0%
#4690000
b101 /
b11100000 +
1%
#4700000
0%
#4710000
b11100001 +
b110 /
1%
#4720000
0%
#4730000
b111 /
b11100010 +
1%
#4740000
0%
#4750000
b11100011 +
b1000 /
1%
#4760000
0%
#4770000
b1001 /
b11100100 +
1%
#4780000
0%
#4790000
b11100101 +
b1010 /
1%
#4800000
0%
#4810000
b1011 /
b11100110 +
1%
#4820000
0%
#4830000
b11100111 +
b1100 /
1%
#4840000
0%
#4850000
b1101 /
b11101000 +
1%
#4860000
0%
#4870000
b11101001 +
b1110 /
1%
#4880000
0%
#4890000
b1111 /
b11101010 +
1%
#4900000
0%
#4910000
b11101011 +
b10000 /
1%
#4920000
0%
#4930000
b10001 /
b11101100 +
1%
#4940000
0%
#4950000
b11101101 +
b10010 /
1%
#4960000
0%
#4970000
b10011 /
b11101110 +
1%
#4980000
0%
#4990000
b11101111 +
b10100 /
1%
#5000000
0%
#5010000
b10101 /
b11110000 +
1%
#5020000
0%
#5030000
b11110001 +
b10110 /
1%
#5040000
0%
#5050000
b10111 /
b11110010 +
1%
#5060000
0%
#5070000
b11110011 +
b11000 /
1%
#5080000
0%
#5090000
b11001 /
b11110100 +
1%
#5100000
0%
#5110000
b11110101 +
b11010 /
1%
#5120000
0%
#5130000
b11011 /
b11110110 +
1%
#5140000
0%
#5150000
b11110111 +
b11100 /
1%
#5160000
0%
#5170000
b11101 /
b11111000 +
1%
#5180000
0%
#5190000
b11111001 +
b11110 /
1%
#5200000
0%
#5210000
b11111 /
b11111010 +
1%
#5220000
0%
#5230000
b11111011 +
b100000 /
1%
#5240000
0%
#5250000
b100001 /
b11111100 +
1%
#5260000
0%
#5270000
b11111101 +
b100010 /
1%
#5280000
0%
#5290000
b100011 /
b11111110 +
1%
#5300000
0%
#5310000
b11111111 +
b100100 /
1%
#5320000
0%
#5330000
b100101 /
b100000000 +
1%
#5340000
0%
#5350000
b100000001 +
b100110 /
1%
#5360000
0%
#5370000
b100111 /
b100000010 +
1%
#5380000
0%
#5390000
b100000011 +
b101000 /
1%
#5400000
0%
#5410000
b101001 /
b100000100 +
1%
#5420000
0%
#5430000
b100000101 +
b101010 /
1%
#5440000
0%
#5450000
b101011 /
b100000110 +
1%
#5460000
0%
#5470000
b100000111 +
b101100 /
1%
#5480000
0%
#5490000
b101101 /
b100001000 +
1%
#5500000
0%
#5510000
b100001001 +
b101110 /
1%
#5520000
0%
#5530000
b101111 /
b100001010 +
1%
#5540000
0%
#5550000
b100001011 +
b110000 /
1%
#5560000
0%
#5570000
b110001 /
b100001100 +
1%
#5580000
0%
#5590000
b100001101 +
b110010 /
1%
#5600000
0%
#5610000
b110011 /
b100001110 +
1%
#5620000
0%
#5630000
b100001111 +
b110100 /
1%
#5640000
0%
#5650000
b110101 /
b100010000 +
1%
#5660000
0%
#5670000
b100010001 +
b110110 /
1%
#5680000
0%
#5690000
b110111 /
b100010010 +
1%
#5700000
0%
#5710000
b100010011 +
b111000 /
1%
#5720000
0%
#5730000
b111001 /
b100010100 +
1%
#5740000
0%
#5750000
b100010101 +
b111010 /
1%
#5760000
0%
#5770000
b111011 /
b100010110 +
1%
#5780000
0%
#5790000
b100010111 +
b111100 /
1%
#5800000
0%
#5810000
b111101 /
b100011000 +
1%
#5820000
0%
#5830000
b100011001 +
b111110 /
1%
#5840000
0%
#5850000
b111111 /
b100011010 +
1%
#5860000
0%
#5870000
b100011011 +
b1000000 /
1%
#5880000
0%
#5890000
b1000001 /
b100011100 +
1%
#5900000
0%
#5910000
b100011101 +
b1000010 /
1%
#5920000
0%
#5930000
b1000011 /
b100011110 +
1%
#5940000
0%
#5950000
b100011111 +
b1000100 /
1%
#5960000
0%
#5970000
b1000101 /
b100100000 +
1%
#5980000
0%
#5990000
b100100001 +
b1000110 /
1%
#6000000
0%
#6010000
b1000111 /
b100100010 +
1%
#6020000
0%
#6030000
b100100011 +
b1001000 /
1%
#6040000
0%
#6050000
b1001001 /
b100100100 +
1%
#6060000
0%
#6070000
b100100101 +
b1001010 /
1%
#6080000
0%
#6090000
b1001011 /
b100100110 +
1%
#6100000
0%
#6110000
b100100111 +
b1001100 /
1%
#6120000
0%
#6130000
b1001101 /
b100101000 +
1%
#6140000
0%
#6150000
b100101001 +
b1001110 /
1%
#6160000
0%
#6170000
b1001111 /
b100101010 +
1%
#6180000
0%
#6190000
b100101011 +
b1010000 /
1%
#6200000
0%
#6210000
b1010001 /
b100101100 +
1%
#6220000
0%
#6230000
b100101101 +
b1010010 /
1%
#6240000
0%
#6250000
b1010011 /
b100101110 +
1%
#6260000
0%
#6270000
b100101111 +
b1010100 /
1%
#6280000
0%
#6290000
b1010101 /
b100110000 +
1%
#6300000
0%
#6310000
b100110001 +
b1010110 /
1%
#6320000
0%
#6330000
b1010111 /
b100110010 +
1%
#6340000
0%
#6350000
b100110011 +
b1011000 /
1%
#6360000
0%
#6370000
b1011001 /
b100110100 +
1%
#6380000
0%
#6390000
b100110101 +
b1011010 /
1%
#6400000
0%
#6410000
b1011011 /
b100110110 +
1%
#6420000
0%
#6430000
b100110111 +
b1011100 /
1%
#6440000
0%
#6450000
b1011101 /
b100111000 +
1%
#6460000
0%
#6470000
b100111001 +
b1011110 /
1%
#6480000
0%
#6490000
b1011111 /
b100111010 +
1%
#6500000
0%
#6510000
b100111011 +
b1100000 /
1%
#6520000
0%
#6530000
b1100001 /
b100111100 +
1%
#6540000
0%
#6550000
b100111101 +
b1100010 /
1%
#6560000
0%
#6570000
b1100011 /
b100111110 +
1%
#6580000
0%
#6590000
b100111111 +
b1100100 /
1%
#6600000
0%
#6610000
b1100101 /
b101000000 +
1%
#6620000
0%
#6630000
b101000001 +
b1100110 /
1%
#6640000
0%
#6650000
b1100111 /
b101000010 +
1%
#6660000
0%
#6670000
b101000011 +
b1101000 /
1%
#6680000
0%
#6690000
b1101001 /
b101000100 +
1%
#6700000
0%
#6710000
b101000101 +
b1101010 /
1%
#6720000
0%
#6730000
b1101011 /
b101000110 +
1%
#6740000
0%
#6750000
b101000111 +
b1101100 /
1%
#6760000
0%
#6770000
b1101101 /
b101001000 +
1%
#6780000
0%
#6790000
b101001001 +
b1101110 /
1%
#6800000
0%
#6810000
b1101111 /
b101001010 +
1%
#6820000
0%
#6830000
b101001011 +
b1110000 /
1%
#6840000
0%
#6850000
b1110001 /
b101001100 +
1%
#6860000
0%
#6870000
b101001101 +
b1110010 /
1%
#6880000
0%
#6890000
b1110011 /
b101001110 +
1%
#6900000
0%
#6910000
b101001111 +
b1110100 /
1%
#6920000
0%
#6930000
b1110101 /
b101010000 +
1%
#6940000
0%
#6950000
b101010001 +
b1110110 /
1%
#6960000
0%
#6970000
b1110111 /
b101010010 +
1%
#6980000
0%
#6990000
b101010011 +
b1111000 /
1%
#7000000
0%
#7010000
b1111001 /
b101010100 +
1%
#7020000
0%
#7030000
b101010101 +
b1111010 /
1%
#7040000
0%
#7050000
b1111011 /
b101010110 +
1%
#7060000
0%
#7070000
b101010111 +
b1111100 /
1%
#7080000
0%
#7090000
b1111101 /
b101011000 +
1%
#7100000
0%
#7110000
b101011001 +
b1111110 /
1%
#7120000
0%
#7130000
b1111111 /
b101011010 +
1%
#7140000
0%
#7150000
b101011011 +
b10000000 /
1%
#7160000
0%
#7170000
b10000001 /
b101011100 +
1%
#7180000
0%
#7190000
b101011101 +
b10000010 /
1%
#7200000
0%
#7210000
b10000011 /
b101011110 +
1%
#7220000
0%
#7230000
b101011111 +
b10000100 /
1%
#7240000
0%
#7250000
b10000101 /
b101100000 +
1%
#7260000
0%
